rnaseqdata/__init__.py
rnaseqdata/annot_data.py
rnaseqdata/bin.py
rnaseqdata/node_data.py
rnaseqdata/random_data.py
rnaseqdata/root_data.py
rnaseqdata/seq_data.py
rnaseqdata/stat_data.py
rnaseqdata-0.0.8.dist-info/LICENSE
rnaseqdata-0.0.8.dist-info/METADATA
rnaseqdata-0.0.8.dist-info/WHEEL
rnaseqdata-0.0.8.dist-info/top_level.txt
rnaseqdata-0.0.8.dist-info/RECORD
