Metadata-Version: 2.1
Name: rnaseqdata
Version: 0.0.8
Summary: New Data type known as SeqData for RNA-Seq data analysis
Home-page: https://github.com/Tiezhengyuan/ernav2_seqdata
Author: Tiezheng Yuan
Author-email: tiezhengyuan@hotmail.com
Keywords: pypi,cicd,python
Classifier: Development Status :: 1 - Planning
Classifier: Intended Audience :: Developers
Classifier: Programming Language :: Python :: 3
Classifier: Operating System :: Unix
Classifier: Operating System :: MacOS :: MacOS X
Classifier: Operating System :: Microsoft :: Windows
License-File: LICENSE
Requires-Dist: numpy
Requires-Dist: pandas
